pytwitchchat/__init__.py
pytwitchchat/py_twitch_chat.py
pytwitchchat-0.1.0.dist-info/LICENSE
pytwitchchat-0.1.0.dist-info/METADATA
pytwitchchat-0.1.0.dist-info/WHEEL
pytwitchchat-0.1.0.dist-info/top_level.txt
pytwitchchat-0.1.0.dist-info/RECORD
